evolite/__about__.py
evolite/__init__.py
evolite/core/__init__.py
evolite-0.0.1.dist-info/METADATA
evolite-0.0.1.dist-info/WHEEL
evolite-0.0.1.dist-info/licenses/LICENSE
evolite-0.0.1.dist-info/RECORD
