Metadata-Version: 2.4
Name: EvoLite
Version: 0.0.1
Summary: An Evolutionary Approach to Neural Network Compression
Project-URL: Documentation, https://brunofaria1322.github.io/EvoLite/
Project-URL: Issues, https://github.com/brunofaria1322/EvoLite/issues
Project-URL: Source, https://github.com/brunofaria1322/EvoLite
Author-email: Bruno Faria <brunofaria@dei.uc.pt>
Maintainer-email: Bruno Faria <brunofaria@dei.uc.pt>
License-Expression: MIT
License-File: LICENSE
Keywords: compression,evolutionary,neural networks,optimization
Classifier: Development Status :: 4 - Beta
Classifier: License :: OSI Approved :: MIT License
Classifier: Operating System :: OS Independent
Classifier: Programming Language :: Python
Classifier: Programming Language :: Python :: 3
Classifier: Programming Language :: Python :: 3.8
Classifier: Programming Language :: Python :: 3.9
Classifier: Programming Language :: Python :: 3.10
Classifier: Programming Language :: Python :: 3.11
Classifier: Programming Language :: Python :: 3.12
Requires-Python: >=3.8
